rallytt/Asset.py
rallytt/File.py
rallytt/Job.py
rallytt/Preset.py
rallytt/Rally.py
rallytt/SupplyChain.py
rallytt/Test.py
rallytt/__init__.py
rallytt/functions.py
rallytt-0.3.8.dist-info/METADATA
rallytt-0.3.8.dist-info/WHEEL
rallytt-0.3.8.dist-info/top_level.txt
rallytt-0.3.8.dist-info/RECORD
