Metadata-Version: 2.1
Name: rallytt
Version: 0.3.8
Summary: Integration/E2E test tools for SDVI Rally
Home-page: UNKNOWN
Author: Carson O'Ffill
Author-email: offillcarson@gmail.com
License: UNKNOWN
Keywords: python,sdvi rally,integration test,end to end test,e2e test,testing tools
Platform: UNKNOWN
Classifier: Development Status :: 3 - Alpha
Classifier: Intended Audience :: Developers
Classifier: Programming Language :: Python :: 3
Classifier: Operating System :: MacOS :: MacOS X
Classifier: Operating System :: Microsoft :: Windows
Requires-Dist: requests
Requires-Dist: colorama
Requires-Dist: redis
